Workbook

Sheet MEMBRESIA
E1: Dig.·. Resp.·. Abn.·. y Sesquicent.·. Log.·. Simb.·. FRATERNIDAD No. 1
B2: MEMBRESÍA Y CONTROL DE APORTACIONES 2 0 2 6
C3: PRICA | D3: AGO | E3: SEP | F3: OCT | G3: NOV | H3: NOV | I3: DIC | J3: ENE | K3: FEB | L3: MAR | M3: ABR | N3: MAY | O3: JUN | P3: JUL | Q3: AGO | R3: SEP | S3: OCT | T3: NOV | U3: DIC | V3: ADEUDO | W3: A FAVOR
A4: 1 | B4: DAVID GARCIA MELGOZA | J4: 1 | K4: 15 | L4: 24 | M4: 47 | N4: 59 | O4: 59 | P4: 73 | Q4: 73 | Z4: 1 | AA4: 21 | AB4: 41 | AC4: 61
A5: 2 | B5: GABINO S. SANTAMARIA DELGADO | J5: 9 | K5: 10 | L5: 23 | M5: 50 | N5: 58 | O5: 65 | P5: 71 | Z5: 2 | AA5: 22 | AB5: 42 | AC5: 62
A6: 3 | B6: JORGE L. MENDOZA SORIANO | J6: 11 | K6: 11 | L6: 39 | M6: 39 | N6: 54 | O6: 54 | Z6: 3 | AA6: 23 | AB6: 43 | AC6: 63
A7: 4 | B7: LEOPOLDO GARCIA MELGOZA | J7: 7 | K7: 34 | L7: 40 | M7: 49 | N7: x | O7: X | Z7: 4 | AA7: 24 | AB7: 44 | AC7: 64
A8: 5 | B8: LUIS RODRIGUEZ MATA | J8: 21 | K8: 21 | L8: 21 | M8: 48 | N8: 48 | O8: 48 | Z8: 5 | AA8: 25 | AB8: 45 | AC8: 65
A9: 6 | B9: L. ENRIQUE RAMON VILABOA | C9: 128 | J9: 14 | K9: 14 | L9: 14 | M9: 14 | N9: 14 | O9: 66 | P9: 67 | Q9: 67 | R9: 67 | S9: 67 | T9: 67 | Z9: 6 | AA9: 26 | AB9: 46 | AC9: 66
A10: 7 | B10: AULIO C. IBARRA ZAVALA | J10: 8 | K10: 8 | L10: 37 | M10: 37 | N10: 52 | O10: 52 | P10: 72 | Q10: 72 | Z10: 7 | AA10: 27 | AB10: 47 | AC10: 67
A11: 8 | B11: GUILLERMO F. MOTOLINIA SANCHEZ | C11: 43 | J11: 43 | K11: 43 | L11: 43 | M11: 43 | N11: 43 | O11: X | Z11: 8 | AA11: 28 | AB11: 48 | AC11: 68
A12: 9 | B12: JOSE A. GONZALEZ SOLIS | I12: 16 | J12: 16 | K12: 16 | L12: 41 | M12: 53 | N12: 70 | O12: 70 | V12: 350 | Z12: 9 | AA12: 29 | AB12: 49 | AC12: 69
A13: 10 | B13: J. OMAR PACHECO TAPIA | J13: 17 | K13: 17 | L13: 32 | M13: 44 | N13: 56 | O13: 64 | P13: 69 | Z13: 10 | AA13: 30 | AB13: 50 | AC13: 70
A14: 11 | B14: RAFAEL MARTINEZ DE JESUS | J14: 13 | K14: 13 | L14: 13 | M14: 13 | N14: 13 | O14: 13 | P14: 20 | Q14: 20 | R14: 20 | S14: 20 | T14: 20 | U14: 31 | Z14: 11 | AA14: 31 | AB14: 51 | AC14: 71
A15: 12 | B15: VICTOR H. AMBROSIO GUEVARA | C15: 26 | I15: 12 | J15: 2 | K15: 26 | L15: 36 | M15: 36 | N15: 57 | O15: 57 | Z15: 12 | AA15: 32 | AB15: 52 | AC15: 72
A16: 13 | B16: ALEXIS GARCIA ROBLES | J16: 33 | K16: 33 | L16: 42 | M16: 51 | N16: 60 | O16: 68 | Z16: 13 | AA16: 33 | AB16: 53 | AC16: 73
A17: 14 | B17: ANGEL R. GUTIERREZ ALVAREZ | J17: 19 | K17: 19 | L17: 19 | M17: 61 | N17: 61 | O17: 61 | P17: 62 | Q17: 62 | R17: 62 | V17: 350 | Z17: 14 | AA17: 34 | AB17: 54 | AC17: 74
A18: 15 | B18: A. RICARDO GUTIERREZ CONTRERAS | J18: 6 | K18: 22 | L18: 30 | M18: 45 | N18: 55 | O18: 63 | Z18: 15 | AA18: 35 | AB18: 55 | AC18: 75
B19: JOSMAR G. CANCHE HERMANDEZ | C19: 4 | D19: 4 | E19: 4 | F19: 4 | G19: 4 | I19: 4 | J19: 5 | K19: 5 | L19: 46 | M19: BAJA EN ABRIL | Z19: 16 | AA19: 36 | AB19: 56 | AC19: 76
B20: L. ELISEO JUAREZ MORALES | C20: 128 | I20: 18 | J20: 18 | K20: 25 | L20: X | M20: X | N20: BAJA EN MAYO | V20: 700 | Z20: 17 | AA20: 37 | AB20: 57 | AC20: 77
B21: L. MANUEL SANCHEZ TELLEZ | H21: 35 | I21: 35 | J21: x | K21: x | L21: X | M21: BAJA EN MARZO | V21: 1050 | Z21: 18 | AA21: 38 | AB21: 58 | AC21: 78
K22: DATOS AL 23 DE MARZO 2026 | Z22: 19 | AA22: 39 | AB22: 59 | AC22: 79
D23: PAGADO Y NUMERO DE RECIBO | Z23: 20 | AA23: 40 | AB23: 60 | AC23: 80

Sheet INGRESOS Y EGRESOS
D1: Dig.·. Resp.·. Abn.·. y Sesquicent.·. Log.·. Simb.·. FRATERNIDAD No. 1
B3: INGRESOS Y EGRESOS DEL MES DE ENERO 2026
B4: CAPITAS: | C4: 300 | E4: ANIVERSARIO: | G4: 50 | I4: MIEMBROS | J4: 18
E6: I N G R E S O S | J6: ENERO DE 2026
A7: RECIBO | B7: M I E M B R O | E7: CAPITAS | F7: ANIV. | G7: SACO BEN. | H7: TALLER B.J. | I7: OTROS | J7: TOTAL | K7: FECHA | L7: DESCRIPCION
A8: S/N | B8: SACO BENEFICENCIA | E8: 0 | F8: 0 | G8: 372 | H8: 0 | I8: 0 | J8: =SUM(E8+F8+G8+H8+I8) -> 372 | K8: 46035 | L8: INSTALACION C.L.
B9: SACO BENEFICENCIA | G9: 147 | J9: =SUM(E9+F9+G9+H9+I9) -> 147 | K9: 46042
B10: SACO BENEFICENCIA | G10: 190 | I10: 0 | J10: =SUM(E10+F10+G10+H10+I10) -> 190 | K10: 46049
A11: 001 | B11: DAVID GARCIA MELGOZA | E11: 285 | F11: 50 | H11: 15 | J11: =SUM(E11+F11+G11+H11+I11) -> 350
A12: 002 | B12: VICTOR H. AMBROSIO GUEVARA | E12: 285 | F12: 50 | H12: 15 | J12: =SUM(E12+F12+G12+H12+I12) -> 350
A13: 003 | B13: LEOPOLDO GARCIA MELGOZA | E13: 5000 | I13: 0 | J13: =SUM(E13+F13+G13+H13+I13) -> 5000 | K13: 46049 | L13: SALDO DE CAPITAS DEL AÑO PASADO
A14: 004 | B14: JOSMAR G. CANCHÉ HERNANDEZ | E14: 1050 | F14: 250 | I14: 128 | J14: =SUM(E14+F14+G14+H14+I14) -> 1428 | K14: 46052 | L14: CAP. AGO-DIC/2025 APOYO POZA RICA
A15: 005 | B15: JOSMAR G. CANCHÉ HERNANDEZ | E15: 570 | F15: 100 | H15: 30 | I15: 0 | J15: =SUM(E15+F15+G15+H15+I15) -> 700 | K15: 46052 | L15: ENE-FEB 2026
A16: 006 | B16: ANGEL R. GUTIERREZ CONTRERAS | E16: 285 | F16: 50 | H16: 15 | J16: =SUM(E16+F16+G16+H16+I16) -> 350 | K16: 46052
J17: =SUM(E17+F17+G17+H17+I17) -> 0
E18: =SUM(E8:E17) -> 7475 | F18: =SUM(F8:F17) -> 500 | G18: =SUM(G8:G17) -> 709 | H18: =SUM(H8:H17) -> 75 | I18: =SUM(I8:I17) -> 128 | J18: =SUM(E18+F18+G18+H18+I18) -> 8887
C21: EGRESOS
A22: No. | B22: C O N C E P T O | E22: CUENTA DE CARGO | K22: FECHA | L22: JUSTIFICACION
E23: CAPITAS | F23: ANIVERS. | G23: SACO BENE | H23: TALLER B.J. | I23: OTROS | J23: TOTAL
A24: 1 | B24: PAGO A LA GRAN LOGIA ENERO 2026 | E24: 5584 | K24: 46056
A25: 2 | B25: COPIAS DE RECIBOS LOGIA | E25: 90
E29: =SUM(E24:E28) -> 5674 | F29: =SUM(F24:F28) -> 0 | G29: =SUM(G24:G28) -> 0 | H29: =SUM(H24:H28) -> 0 | I29: =SUM(I24:I28) -> 0 | J29: =E29+F29+G29+H29+I29 -> 5674
H31: REMANENTE DEL MES | J31: =J18-J29 -> 3213
B34: ELABORÓ | E34: REVISÓ | J34: AUTORIZÓ
B36: DAVID GARCIA MELGOZA | E36: LEOPOLDO GARCIA MELGOZA | J36: GABINO S. SANTAMARIA DELGADO
B37: TES:. | E37: PDTE. COMISION DE HDA. | J37: VEN:. MAES:.
D66: Dig.·. Resp.·. Abn.·. y Sesquicent.·. Log.·. Simb.·. FRATERNIDAD No. 1
B68: INGRESOS Y EGRESOS DEL MES DE FEBRERO 2026
B69: CAPITAS: | C69: 300 | E69: ANIVERSARIO: | G69: 50 | I69: MIEMBROS | J69: 18
E71: I N G R E S O S
A72: RECIBO | B72: M I E M B R O | E72: CAPITAS | F72: ANIV. | G72: SACO BEN. | H72: TALLER B.J. | I72: OTROS | J72: TOTAL | K72: FECHA | L72: DESCRIPCION
A73: S/N | B73: SACO BENEFICENCIA | E73: 0 | F73: 0 | G73: 190 | H73: 0 | I73: 0 | J73: =SUM(E73+F73+G73+H73+I73) -> 190 | K73: 46056
A74: N7 | B74: LEOPOLDO GARCIA M. | E74: 285 | F74: 50 | G74: 0 | H74: 15 | I74: 0 | J74: =SUM(E74+F74+G74+H74+I74) -> 350 | K74: 46056 | L74: PAGO ENERO 2026
A75: N8 | B75: AULIO C. IBARRA Z. | E75: 570 | F75: 100 | H75: 30 | J75: =SUM(E75+F75+G75+H75+I75) -> 700 | K75: 46056 | L75: PAGO ENE-FEB 26
A76: N9 | B76: GABINO S.SANTAMARIA D. | E76: 285 | F76: 50 | H76: 15 | J76: =SUM(E76+F76+G76+H76+I76) -> 350 | K76: 46056 | L76: PAGO ENERO 2026
A77: 10 | B77: GABINO S.SANTAMARIA D. | E77: 285 | F77: 50 | H77: 15 | J77: =SUM(E77+F77+G77+H77+I77) -> 350 | K77: 46063 | L77: PAGO FEB 2026
A78: 11 | B78: JORGE L.MENDOZA S. | E78: 570 | F78: 100 | H78: 30 | J78: =SUM(E78+F78+G78+H78+I78) -> 700 | K78: 46063 | L78: PAGO ENE-FEB 26
A79: 12 | B79: VICTOR H. AMBROSIO G. | E79: 250 | F79: 50 | H79: 0 | J79: =SUM(E79+F79+G79+H79+I79) -> 300 | K79: 46063 | L79: PAGO DIC 2025
A80: S/N | B80: SACO BENEFICENCIA | G80: 250 | J80: =SUM(E80+F80+G80+H80+I80) -> 250 | K80: 46063
A81: 13 | B81: RAFAEL MARTINEZ DE J. | E81: 1710 | F81: 300 | H81: 90 | J81: =SUM(E81+F81+G81+H81+I81) -> 2100 | K81: 46063 | L81: PAGO ENE-JUN 26
A82: 14 | B82: LUIS ENRIQUE RAMON V. | E82: 1425 | F82: 250 | H82: 75 | J82: =SUM(E82+F82+G82+H82+I82) -> 1750 | K82: 46058 | L82: PAGO ENE-MAY 26
A83: 15 | B83: DAVID GARCIA M. | E83: 285 | F83: 50 | H83: 15 | J83: =SUM(E83+F83+G83+H83+I83) -> 350 | K83: 46073 | L83: PAGO FEB 2026 | N83: MESES | O83: 350 | P83: 400
A84: 16 | B84: JOSE ALFREDO GONZALEZ S. | E84: 820 | F84: 150 | H84: 30 | J84: =SUM(E84+F84+G84+H84+I84) -> 1000 | K84: 46076 | L84: DIC/25 Y ENE-FEB/26 | N84: 1 | O84: 285 | P84: 335
A85: 17 | B85: JOSE OMAR PACHECO T. | E85: 570 | F85: 100 | H85: 30 | J85: =SUM(E85+F85+G85+H85+I85) -> 700 | K85: 46076 | L85: ENE-FEB/26 | N85: 2 | O85: =285*2 -> 570 | P85: =2*P84 -> 670
A86: 18 | B86: LUIS ELISEO JUAREZ M. | E86: 535 | F86: 100 | H86: 15 | J86: =SUM(E86+F86+G86+H86+I86) -> 650 | K86: 46077 | L86: DIC/25 Y ENE/26 | N86: 3 | O86: =285*3 -> 855 | P86: =3*P84 -> 1005
A87: 20 | B87: RAFAEL MARTINEZ DEL A. | E87: 1675 | F87: 250 | H87: 75 | J87: =SUM(E87+F87+G87+H87+I87) -> 2000 | K87: 46079 | L87: JUL-NOV/26 100 A FAVOR | N87: 4 | O87: =285*4 -> 1140 | P87: =4*P84 -> 1340
A88: 22 | B88: A. RICARDO GUTIERREZ C. | E88: 285 | F88: 50 | G88: 0 | H88: 15 | I88: 0 | J88: =SUM(E88+F88+G88+H88+I88) -> 350 | K88: 25 FE | L88: CAP. FEBRERO | N88: 5 | O88: =285*5 -> 1425 | P88: =5*P84 -> 1675
E89: =SUM(E73:E88) -> 9550 | F89: =SUM(F73:F88) -> 1650 | G89: =SUM(G73:G88) -> 440 | H89: =SUM(H73:H88) -> 450 | I89: =SUM(I73:I88) -> 0 | J89: =SUM(E89+F89+G89+H89+I89) -> 12090 | N89: 6 | O89: =285*6 -> 1710 | P89: =6*P84 -> 2010
C92: EGRESOS
A93: No. | B93: C O N C E P T O | E93: CUENTA DE CARGO | K93: FECHA | L93: JUSTIFICACION
E94: CAPITAS | F94: ANIVERS. | G94: SACO BENE | H94: TALLER B.J. | I94: OTROS | J94: TOTAL
A95: 1 | B95: COMPRA DE PAPELERIA | E95: 160 | J95: =E95+F95+G95+H95+I95 -> 160
A96: 2 | B96: PAGO A GLUM MES FEB/26 | E96: 4584
A97: 3 | B97: APERT. CTA. BANCO | E97: 100
E100: =SUM(E95:E99) -> 4844 | F100: =SUM(F95:F99) -> 0 | G100: =SUM(G95:G99) -> 0 | H100: =SUM(H95:H99) -> 0 | I100: =SUM(I95:I99) -> 0 | J100: =E100+F100+G100+H100+I100 -> 4844
H102: REMANENTE DEL MES | J102: =J89-J100 -> 7246
B104: ELABORÓ | E104: REVISÓ | J104: AUTORIZÓ
B106: DAVID GARCIA MELGOZA | E106: LEOPOLDO GARCIA MELGOZA | J106: GABINO S. SANTAMARIA DELGADO
B107: TES:. | E107: PDTE. COMISION DE HDA. | J107: VEN:. MAES:.
D132: Dig.·. Resp.·. Abn.·. y Sesquicent.·. Log.·. Simb.·. FRATERNIDAD No. 1
B134: INGRESOS Y EGRESOS DEL MES DE MARZO 2026
B135: CAPITAS: | C135: 300 | E135: ANIVERSARIO: | G135: 50 | I135: MIEMBROS | J135: 17
E137: I N G R E S O S
A138: RECIBO | B138: M I E M B R O | E138: CAPITAS | F138: ANIV. | G138: SACO BEN. | H138: TALLER B.J. | I138: OTROS | J138: TOTAL | K138: FECHA | L138: DESCRIPCION
A139: 19 | B139: ANGEL R. GUTIERREZ A. | E139: 905 | F139: 150 | H139: 45 | J139: =SUM(E139+F139+G139+H139+I139) -> 1100 | L139: DE POLO ENE-MAR/2026 50 A FAVOR
A140: 21 | B140: LUIS RODRIGUEZ M | E140: 855 | F140: 150 | G140: 0 | H140: 45 | I140: 0 | J140: =SUM(E140+F140+G140+H140+I140) -> 1050 | K140: 46079 | L140: ENE-MAR/2026
A141: 23 | B141: GABINO S. SANTAMARIA | E141: 285 | F141: 50 | G141: 0 | H141: 15 | I141: 0 | J141: =SUM(E141+F141+G141+H141+I141) -> 350 | K141: 46084 | L141: CAPS. MAR/2026
A142: 24 | B142: DAVID GARCIA M. | E142: 285 | F142: 50 | H142: 15 | J142: =SUM(E142+F142+G142+H142+I142) -> 350 | K142: 46084 | L142: CAPS. MAR/2026 | N142: RECIBOS 19 Y 29 DEVOLUCIONES DE LEOPOLDO
A143: 25 | B143: LUIS ELISEO JUAREZ M. | E143: 285 | F143: 50 | H143: 15 | J143: =SUM(E143+F143+G143+H143+I143) -> 350 | K143: 46084 | L143: CAPS. FEB/2026
A144: 26 | B144: VICTOR H. AMBROSIO G. | E144: 307 | F144: 50 | H144: 15 | I144: 128 | J144: =SUM(E144+F144+G144+H144+I144) -> 500 | K144: 46084 | L144: P.RICA , FEB/2026 22 PESOS A FAVOR
A145: 27 | B145: LEOPOLDO GARCIA M. | E145: 0 | F145: 6344 | H145: 0 | J145: =SUM(E145+F145+G145+H145+I145) -> 6344 | K145: 46084 | L145: FONDO ANIVERSARI
A146: 28 | B146: LEOPOLDO GARCIA M. | E146: 5320.5 | F146: 0 | H146: 0 | J146: =SUM(E146+F146+G146+H146+I146) -> 5320.5 | K146: 46084 | L146: FONDO DE CAPITAS
A147: 29 | B147: C A N C E L A D O
A148: 30 | B148: A. RICARDO GUTIERREZ C. | E148: 285 | F148: 50 | H148: 15 | J148: =SUM(E148+F148+G148+H148+I148) -> 350 | K148: 46085 | L148: CAP. MAR/2026
A149: 31 | B149: RAFAEL MARTINEZ DE J. | E149: 335 | F149: 50 | H149: 15 | J149: =SUM(E149+F149+G149+H149+I149) -> 400 | K149: 46085 | L149: CAP. DIC/2026
A150: 32 | B150: OMAR PACHECO T. | E150: 285 | F150: 50 | H150: 15 | J150: =SUM(E150+F150+G150+H150+I150) -> 350 | K150: 46085 | L150: CAP. MAR/2026 | N150: MESES | O150: 350 | P150: 400
A151: 33 | B151: ALEXIS GARCIA ROBLES | E151: 570 | F151: 100 | H151: 30 | J151: =SUM(E151+F151+G151+H151+I151) -> 700 | K151: 46086 | L151: CAP. ENE-FEB726 | N151: 1 | O151: 285 | P151: 335
A152: 34 | B152: LEOPOLDO GARCIA M. | E152: 285 | F152: 50 | H152: 15 | J152: =SUM(E152+F152+G152+H152+I152) -> 350 | K152: 46086 | L152: CAP. FEBRERO/2026 | N152: 2 | O152: =285*2 -> 570 | P152: 670
A153: 35 | B153: L. MANUEL GONZALEZ T. | E153: 322 | F153: 50 | H153: 0 | I153: 128 | J153: =SUM(E153+F153+G153+H153+I153) -> 500 | K153: 46087 | L153: P.R.+ NOV-DIC/2025 | N153: 3 | O153: =285*3 -> 855 | P153: 1005
A154: 36 | B154: VICTOR H. AMBROSIO G. | E154: 570 | F154: 100 | H154: 30 | J154: =SUM(E154+F154+G154+H154+I154) -> 700 | K154: 46087 | L154: MAR-ABR/2026 | N154: 4 | O154: =285*4 -> 1140 | P154: 1340
A155: 37 | B155: AULIO C. IBARRA Z. | E155: 570 | F155: 100 | H155: 30 | J155: =SUM(E155+F155+G155+H155+I155) -> 700 | K155: 46091 | L155: CAP. MAR-ABR/26
A156: 38 | B156: LEOPOLDO GARCIA M. | E156: 855 | J156: =SUM(E156+F156+G156+H156+I156) -> 855 | K156: 46091 | L156: ENTREGA TESORERIA
A157: 39 | B157: JORGE L. MENDOZA S. | E157: 570 | F157: 100 | H157: 30 | J157: =SUM(E157+F157+G157+H157+I157) -> 700 | K157: 46091 | L157: CAP. MAR-ABR/26
B158: SACO BENEFICENCIA | G158: 270 | J158: =SUM(E158+F158+G158+H158+I158) -> 270 | K158: 46084
B159: SACO BENEFICENCIA | G159: 135 | J159: =SUM(E159+F159+G159+H159+I159) -> 135 | K159: 46091
A160: 40 | B160: LEOPOLDO GARCIA M. | E160: 285 | F160: 50 | H160: 15 | J160: =SUM(E160+F160+G160+H160+I160) -> 350 | K160: 46098 | L160: CAP. MAR/2026
A161: 41 | B161: JOSE ALFREDO GONZALEZ S. | E161: 385 | F161: 50 | H161: 15 | I161: 0 | J161: =SUM(E161+F161+G161+H161+I161) -> 450 | K161: 46099 | L161: CAP. MAR Y BOLETO RIFA
B162: SACO BENEFICENCIA | G162: 128 | J162: =SUM(E162+F162+G162+H162+I162) -> 128 | K162: 46098
A163: 42 | B163: ALEXIS GARCIA ROBLES | E163: 285 | F163: 50 | H163: 15 | I163: 0 | J163: =SUM(E163+F163+G163+H163+I163) -> 350 | K163: 46106 | L163: CAP. MAR 2026
B164: DEPOSITO DE CAPITAS A BANCO | E164: 3500 | J164: =SUM(E164+F164+G164+H164+I164) -> 3500
E165: =SUM(E139:E164) -> 17344.5 | F165: =SUM(F139:F163) -> 7644 | G165: =SUM(G139:G163) -> 533 | H165: =SUM(H139:H163) -> 375 | I165: =SUM(I139:I163) -> 256 | J165: =SUM(E165+F165+G165+H165+I165) -> 26152.5 | N165: 6 | O165: =285*6 -> 1710 | P165: 2010
C168: EGRESOS
A169: No. | B169: C O N C E P T O | E169: CUENTA DE CARGO | K169: FECHA | L169: JUSTIFICACION
E170: CAPITAS | F170: ANIVERS. | G170: SACO BENE | H170: TALLER B.J. | I170: OTROS | J170: TOTAL
A171: 1 | B171: COPIAS DE ENTREGA TESOR | E171: 85 | J171: =E171+F171+G171+H171+I171 -> 85
A172: 2 | B172: PAGO A GLUM MES MAR/26 | E172: 4386
A173: 3 | B173: BOLETO RIFA ALFREDO GONZALEZ | E173: 100 | I173: 0
A174: 4 | B174: DEPOSITO DE CAPITAS A BANCO | E174: 3500
E176: =SUM(E171:E175) -> 8071 | F176: =SUM(F171:F175) -> 0 | G176: =SUM(G171:G175) -> 0 | H176: =SUM(H171:H175) -> 0 | I176: =SUM(I171:I175) -> 0 | J176: =E176+F176+G176+H176+I176 -> 8071
H178: REMANENTE DEL MES | J178: =J165-J176 -> 18081.5
...

Sheet INFORME MENS
C3: INFORME MENSUAL DE RESULTADOS FINANCIEROS
B4: MIEMBROS ACTIVOS | D4: 18 | E4: FECHA: | F4: ENERO 2026
C6: CAPITAS
B7: INGRESO | C7: MES ANT. | D7: SUB TOTAL | E7: EGRESO | G7: SALDO TOTAL
B8: ='INGRESOS Y EGRESOS'!E18 -> 7475 | C8: 0 | D8: =B8+C8 -> 7475 | E8: ='INGRESOS Y EGRESOS'!E29 -> 5674 | G8: =D8-E8 -> 1801
C10: ANIVERSARIO
B11: INGRESOS | C11: MES ANT. | D11: SUB TOTAL | E11: EGRESO | G11: SALDO TOTAL
B12: ='INGRESOS Y EGRESOS'!F18 -> 500 | C12: 0 | D12: =B12+C12 -> 500 | E12: 0 | G12: =D12-E12 -> 500
C14: SACO DE BENEFICENCIA
B15: INGRESOS | C15: MES ANT. | D15: SUB TOTAL | E15: EGRESO | G15: SALDO TOTAL
B16: 709 | D16: =B16+C16 -> 709 | E16: 0 | G16: =D16-E16 -> 709
C18: T A L L E R B E N I T O J U A R E Z
B19: INGRESOS | C19: MES ANT. | D19: SUB TOTAL | E19: EGRESO | G19: SALDO TOTAL
B20: 75 | C20: 0 | D20: =B20+C20 -> 75 | E20: 0 | G20: =D20-E20 -> 75
C22: OTROS (Poza Rica)
B23: INGRESOS | C23: MES ANT. | D23: SUB TOTAL | E23: EGRESO | G23: SALDO TOTAL
B24: 128 | C24: 0 | D24: =B24+C24 -> 128 | E24: 0 | G24: =D24-E24 -> 128
E27: SUMA TOTAL | G27: =G8+G12+G16+G20+G24 -> 3213
B30: ELABORÓ | D30: REVISÓ | G30: AUTORIZÓ
A32: DAVID GARCIA MELGOZA | D32: LEOPOLDO GARCIA MELGOZA | G32: GABINO S. SANTAMARIA DELGADO
B33: TES:. | D33: PRESIDENTE COM. HDA. | G33: VEN:. MAES:.
C47: INFORME MENSUAL DE RESULTADOS FINANCIEROS
B48: MIEMBROS ACTIVOS | D48: 18 | E48: FECHA: | F48: FEBRERO 2026
C50: CAPITAS
B51: INGRESO | C51: MES ANT. | D51: SUB TOTAL | E51: EGRESO | G51: SALDO TOTAL
B52: ='INGRESOS Y EGRESOS'!E89 -> 9550 | C52: =G8 -> 1801 | D52: =B52+C52 -> 11351 | E52: ='INGRESOS Y EGRESOS'!E100 -> 4844 | G52: =D52-E52 -> 6507
C54: ANIVERSARIO
B55: INGRESOS | C55: MES ANT. | D55: SUB TOTAL | E55: EGRESO | G55: SALDO TOTAL
B56: ='INGRESOS Y EGRESOS'!F89 -> 1650 | C56: =G12 -> 500 | D56: =B56+C56 -> 2150 | E56: 0 | G56: =D56-E56 -> 2150
C58: SACO DE BENEFICENCIA
B59: INGRESOS | C59: MES ANT. | D59: SUB TOTAL | E59: EGRESO | G59: SALDO TOTAL
B60: ='INGRESOS Y EGRESOS'!G89 -> 440 | C60: =G16 -> 709 | D60: =B60+C60 -> 1149 | E60: 0 | G60: =D60-E60 -> 1149
C62: T A L L E R B E N I T O J U A R E Z
B63: INGRESOS | C63: MES ANT. | D63: SUB TOTAL | E63: EGRESO | G63: SALDO TOTAL
B64: ='INGRESOS Y EGRESOS'!H89 -> 450 | C64: =G20 -> 75 | D64: =B64+C64 -> 525 | E64: 0 | G64: =D64-E64 -> 525
C66: OTROS (Poza Rica)
B67: INGRESOS | C67: MES ANT. | D67: SUB TOTAL | E67: EGRESO | G67: SALDO TOTAL
B68: ='INGRESOS Y EGRESOS'!I89 -> 0 | C68: =G24 -> 128 | D68: =B68+C68 -> 128 | E68: 0 | G68: =D68-E68 -> 128
E71: SUMA TOTAL | G71: =G52+G56+G60+G64+G68 -> 10459
B74: ELABORÓ | D74: REVISÓ | G74: AUTORIZÓ
A76: DAVID GARCIA MELGOZA | D76: LEOPOLDO GARCIA MELGOZA | G76: GABINO S. SANTAMARIA DELGADO
B77: TES:. | D77: PRESIDENTE COM. HDA. | G77: VEN:. MAES:.
C91: INFORME MENSUAL DE RESULTADOS FINANCIEROS
B92: MIEMBROS ACTIVOS | D92: 17 | E92: FECHA: | F92: MARZO 2026
C94: CAPITAS
B95: INGRESO | C95: MES ANT. | D95: SUB TOTAL | E95: EGRESO | G95: SALDO TOTAL
B96: ='INGRESOS Y EGRESOS'!E165 -> 17344.5 | C96: =G52 -> 6507 | D96: =B96+C96 -> 23851.5 | E96: ='INGRESOS Y EGRESOS'!E176 -> 8071 | G96: =D96-E96 -> 15780.5
C98: ANIVERSARIO
B99: INGRESOS | C99: MES ANT. | D99: SUB TOTAL | E99: EGRESO | G99: SALDO TOTAL
B100: ='INGRESOS Y EGRESOS'!F165 -> 7644 | C100: =G56 -> 2150 | D100: =B100+C100 -> 9794 | E100: 0 | G100: =D100-E100 -> 9794
C102: SACO DE BENEFICENCIA
B103: INGRESOS | C103: MES ANT. | D103: SUB TOTAL | E103: EGRESO | G103: SALDO TOTAL
B104: ='INGRESOS Y EGRESOS'!G165 -> 533 | C104: =G60 -> 1149 | D104: =B104+C104 -> 1682 | E104: 0 | G104: =D104-E104 -> 1682
C106: T A L L E R B E N I T O J U A R E Z
B107: INGRESOS | C107: MES ANT. | D107: SUB TOTAL | E107: EGRESO | G107: SALDO TOTAL
B108: ='INGRESOS Y EGRESOS'!H165 -> 375 | C108: =G64 -> 525 | D108: =B108+C108 -> 900 | E108: 0 | G108: =D108-E108 -> 900
C110: OTROS (Poza Rica)
B111: INGRESOS | C111: MES ANT. | D111: SUB TOTAL | E111: EGRESO | G111: SALDO TOTAL
B112: ='INGRESOS Y EGRESOS'!I165 -> 256 | C112: =G68 -> 128 | D112: =B112+C112 -> 384 | E112: 0 | G112: =D112-E112 -> 384
E115: SUMA TOTAL | G115: =G96+G100+G104+G108+G112 -> 28540.5
B118: ELABORÓ | D118: REVISÓ | G118: AUTORIZÓ
A120: DAVID GARCIA MELGOZA | D120: LEOPOLDO GARCIA MELGOZA | G120: GABINO S. SANTAMARIA DELGADO
B121: TES:. | D121: PRESIDENTE COM. HDA. | G121: VEN:. MAES:.
C135: INFORME MENSUAL DE RESULTADOS FINANCIEROS
B136: MIEMBROS ACTIVOS | D136: 16 | E136: FECHA: | F136: ABRIL 2026
C138: CAPITAS
B139: INGRESO | C139: MES ANT. | D139: SUB TOTAL | E139: EGRESO | G139: SALDO TOTAL
B140: ='INGRESOS Y EGRESOS'!E217 -> 4275 | C140: =G96 -> 15780.5 | D140: =B140+C140 -> 20055.5 | E140: ='INGRESOS Y EGRESOS'!E228 -> 5014 | G140: =D140-E140 -> 15041.5
C142: ANIVERSARIO
B143: INGRESOS | C143: MES ANT. | D143: SUB TOTAL | E143: EGRESO | G143: SALDO TOTAL
B144: ='INGRESOS Y EGRESOS'!F217 -> 750 | C144: =G100 -> 9794 | D144: =B144+C144 -> 10544 | E144: 0 | G144: =D144-E144 -> 10544
C146: SACO DE BENEFICENCIA
B147: INGRESOS | C147: MES ANT. | D147: SUB TOTAL | E147: EGRESO | G147: SALDO TOTAL
B148: ='INGRESOS Y EGRESOS'!G217 -> 1100 | C148: =G104 -> 1682 | D148: =B148+C148 -> 2782 | E148: ='INGRESOS Y EGRESOS'!G228 -> 2000 | G148: =D148-E148 -> 782
C150: T A L L E R B E N I T O J U A R E Z
B151: INGRESOS | C151: MES ANT. | D151: SUB TOTAL | E151: EGRESO | G151: SALDO TOTAL
B152: ='INGRESOS Y EGRESOS'!H217 -> 225 | C152: =G108 -> 900 | D152: =B152+C152 -> 1125 | E152: ='INGRESOS Y EGRESOS'!H228 -> 519 | G152: =D152-E152 -> 606
C154: OTROS (Poza Rica)
B155: INGRESOS | C155: MES ANT. | D155: SUB TOTAL | E155: EGRESO | G155: SALDO TOTAL
B156: ='INGRESOS Y EGRESOS'!I217 -> 50 | C156: =G112 -> 384 | D156: =B156+C156 -> 434 | E156: 0 | G156: =D156-E156 -> 434
E159: SUMA TOTAL | G159: =G140+G144+G148+G152+G156 -> 27407.5
B162: ELABORÓ | D162: REVISÓ | G162: AUTORIZÓ
A164: DAVID GARCIA MELGOZA | D164: LEOPOLDO GARCIA MELGOZA | G164: GABINO S. SANTAMARIA DELGADO
B165: TES:. | D165: PRESIDENTE COM. HDA. | G165: VEN:. MAES:.
C179: INFORME MENSUAL DE RESULTADOS FINANCIEROS
B180: MIEMBROS ACTIVOS | D180: 15 | E180: FECHA: | F180: MAYO 2026
C182: CAPITAS
B183: INGRESO | C183: MES ANT. | D183: SUB TOTAL | E183: EGRESO | G183: SALDO TOTAL
B184: ='INGRESOS Y EGRESOS'!E255 -> 1995 | C184: =G140 -> 15041.5 | D184: =B184+C184 -> 17036.5 | E184: ='INGRESOS Y EGRESOS'!E266 -> 3240 | G184: =D184-E184 -> 13796.5
C186: ANIVERSARIO
B187: INGRESOS | C187: MES ANT. | D187: SUB TOTAL | E187: EGRESO | G187: SALDO TOTAL
B188: ='INGRESOS Y EGRESOS'!F255 -> 350 | C188: =G144 -> 10544 | D188: =B188+C188 -> 10894 | E188: 0 | G188: =D188-E188 -> 10894
C190: SACO DE BENEFICENCIA
B191: INGRESOS | C191: MES ANT. | D191: SUB TOTAL | E191: EGRESO | G191: SALDO TOTAL
B192: ='INGRESOS Y EGRESOS'!G255 -> 345 | C192: =G148 -> 782 | D192: =B192+C192 -> 1127 | E192: ='INGRESOS Y EGRESOS'!G264 -> 0 | G192: =D192-E192 -> 1127
C194: T A L L E R B E N I T O J U A R E Z
B195: INGRESOS | C195: MES ANT. | D195: SUB TOTAL | E195: EGRESO | G195: SALDO TOTAL
B196: ='INGRESOS Y EGRESOS'!H255 -> 105 | C196: =G152 -> 606 | D196: =B196+C196 -> 711 | E196: ='INGRESOS Y EGRESOS'!H264 -> 0 | G196: =D196-E196 -> 711
C198: OTROS (Poza Rica)
B199: INGRESOS | C199: MES ANT. | D199: SUB TOTAL | E199: EGRESO | G199: SALDO TOTAL
...

Sheet PAGO A GLUM
C3: Dig.·. Resp.·. Abn.·. y Sesquicent.·. Log.·. Simb.·. FRATERNIDAD No. 1
A4: REMESA DE FONDOS MENSUAL QUE SE RINDE EN CUMPLIMIENTO DE LO QUE DISPONE EL ART. 60 DEL REGLAMENTO DE LA GR:. LOG:.
F5: "UNIDA MEXICANA" Y DE LL:. Y AA:. MM:. DEL GR:. OR:. DE VERACRUZ
B7: RESP:. LOG:. SIMB:. | D7: FRATERNIDAD No. 1
B8: MES : | C8: MARZO 2026
B9: DETALLE DE LA APLICACIÓN | J9: AUX:. MAS:. "POST MORTEM"
B10: CAPITAS | I10: GRAN LOGIA
F11: MES | G11: HH:. | H11: COSTO
B13: MENSUAL | F13: 1 | G13: 17 | H13: 120 | I13: =F13*G13*H13 -> 2040
B14: DERECHOS
B15: INICIACIONES | G15: 0 | H15: 250 | I15: =G15*H15 -> 0
B16: AUMENTO DE SALARIO | G16: 0 | H16: 250 | I16: =G16*H16 -> 0
B17: EXALTACIONES | G17: 0 | H17: 250 | I17: =G17*H17 -> 0
B18: REGULARIZACIONES | G18: 0 | H18: 250 | I18: =G18*H18 -> 0
B19: AFILIACION | G19: 0 | H19: 250 | I19: =G19*H19 -> 0
B21: DIVERSOS
B23: REVISTA UNIDAD MEXICANA (SIMBOLISMO) | F23: =F13 -> 1 | G23: =G13 -> 17 | H23: 18 | I23: =F23*G23*H23 -> 306
B24: CONF:. GGR:. LLOG:. REP.MEX. | F24: 1 | G24: --- | H24: 150 | I24: =F24*H24 -> 150
B25: CONF:. MAS:. INTERAMERICANA | F25: 1 | G25: --- | H25: 70 | I25: =F25*H25 -> 70
B26: SERVICIOS | F26: =F13 -> 1 | G26: --- | H26: 800 | I26: =F26*H26 -> 800
B28: OTROS: FONDO DE CONTINGENCIA | F28: 0 | G28: --- | H28: 500 | I28: =F28*H28 -> 0
B30: AUX:. MAS:. "POST MORTEM"
B32: CUOTAS INICIALES | G32: 0 | H32: 150 | J32: =G32*H32 -> 0
B33: CUOTAS MENSUALES | F33: 1 | G33: =G13 -> 17 | H33: 10 | J33: =F33*G33*H33 -> 170
B34: DEFUNCION No. DEL | C34: 2759 | D34: AL | E34: 2759 | F34: 1 | G34: =G13 -> 17 | H34: 50 | J34: =F34*G34*H34 -> 850
H35: SUBTOTAL | I35: =SUM(I13:I34) -> 3366 | J35: =SUM(J13:J34) -> 1020
H36: TOTAL | I36: =I35+J35 -> 4386
C38: MIEMBROS ACTIVOS | G38: ALTAS EN EL MES | J38: MOVIMIENTOS EN EL MES
C40: 6 | D40: MAESTROS | G40: 0 | H40: INIC. | J40: 0 | K40: AUM. SAL
C41: 6 | D41: COMPAÑEROS | G41: 0 | H41: AFIL. | J41: 0 | K41: EXALT
C42: 5 | D42: APRENDICES | G42: 0 | H42: REG. | J42: =J40+J41 -> 0 | K42: TOTAL
C43: =C40+C41+C42 -> 17 | D43: TOTAL | G43: =G40+G41+G42 -> 0 | H43: TOTAL
C45: BAJAS EN EL MES | J45: OTROS
C46: 0 | D46: BORRADOS POR FALTAS REGLAMENTARIAS | J46: 0 | K46: M.L.O.
C47: 0 | D47: SEPARADOS POR PL:. DE QUITE | J47: 0 | K47: M. ALT. CAM
C48: =C46+C47 -> 0 | D48: TOTAL | J48: =J46+J47 -> 0 | K48: TOTAL
C50: RESUMEN
C51: 18 | D51: MMIEMB.ACTI. MES ANTERIOR
C52: 18 | D52: MMIEMB.ACTI. PRESENTE MES
C53: 0 | D53: DIFERENCIA HH:. DEL TALLER
B57: OR:. DE VERACRUZ, VER. A. | E57: =C8 -> MARZO 2026
G59: Elaboró
F61: DAVID GARCIA MELGOZA
G62: TES:.
D65: Vo. Bo. | I65: Enterado
C67: GABINO S. SANTAMARIA DELGADO | I67: LEOPOLDO GARCIA MELGOZA
C68: VEN:. MAEST:. | I68: PDTE. COMISION DE HDA.
A71: REMESA DE FONDOS MENSUAL QUE SE RINDE EN CUMPLIMIENTO DE LO QUE DISPONE EL ART. 60 DEL REGLAMENTO DE LA GR:. LOG:.
F72: "UNIDA MEXICANA" Y DE LL:. Y AA:. MM:. DEL GR:. OR:. DE VERACRUZ
B75: RESP:. LOG:. SIMB:. "FRATERNIDAD No. 1" OR:. DE VERACRUZ, VER.
B76: RELACION DE MIEMBROS ACTIVOS CORRESPONDIENTE AL : | I76: FECHA | J76: =E57 -> MARZO 2026
D78: NOMBRE Y GRADO
C81: MM:. MM:.
A83: 1 | B83: GABINO SABITRI SANTAMARIA DELGADO | F83: V:. M:.
A84: 2 | B84: LEOPOLDO GARCIA MELGOZA | F84: P:. V:.
A85: 3 | B85: LUIS RODRIGUEZ MATA | F85: S:. V:.
A86: 4 | B86: JORJE LUIS MENDOZA SORIANO | F86: SEC:.
A87: 5 | B87: DAVID GARCIA MELGOZA | F87: ORA:.
A88: 6 | B88: LUIS ENRIQUE RAMON VILABOA | F88: M:. CC:.
C90: CC:. MM:.
A91: 1 | B91: AULIO CESAR IBARRA ZAVALA
A92: 2 | B92: GUILLERMO FRANCISCO MOTOLINIA DELGADO
A93: 3 | B93: JOSE ALFREDO GONZALEZ SOLIS
A94: 4 | B94: JOSE OMAR PACHECO TAPIA
A95: 5 | B95: RAFAEL MARTINEZ DE JESUS
A96: 6 | B96: VICTOR HUGO AMBROSIO GUEVARA
C98: AAP:. MM:.
A99: 1 | B99: ALEXIS GARCIA GUERRA
A100: 2 | B100: ANGEL RICARDO GUTIERREZ ALVAREZ
A101: 3 | B101: ANGEL RICARDO GUTIERREZ CONTRERAS
A102: 4 | B102: JOSMAR GABRIEL CANCHE HERMANDEZ
A103: 5 | B103: LUIS ELISEO JUAREZ MORALES
A104: 6
E107: M:. L:. O:.
B111: ALTAS BAJAS Y MOVIMIENTOS
B113: N O M B R E | F113: GRADO | G113: FECHA | I113: MOVTO. | J113: CONCEPTO DEL MISMO
B114: LUIS MANUEL SANCHEZ TELLEZ | F114: 1 | G114: 46083 | I114: BAJA | J114: FALTA DE ASISTENCIA Y PAGO
C135: Dig.·. Resp.·. Abn.·. y Sesquicent.·. Log.·. Simb.·. FRATERNIDAD No. 1
A136: REMESA DE FONDOS MENSUAL QUE SE RINDE EN CUMPLIMIENTO DE LO QUE DISPONE EL ART. 60 DEL REGLAMENTO DE LA GR:. LOG:.
F137: "UNIDA MEXICANA" Y DE LL:. Y AA:. MM:. DEL GR:. OR:. DE VERACRUZ
B139: RESP:. LOG:. SIMB:. | D139: FRATERNIDAD No. 1
B140: MES : | C140: MARZO 2026
B141: DETALLE DE LA APLICACIÓN | J141: AUX:. MAS:. "POST MORTEM"
B142: CAPITAS | I142: GRAN LOGIA
F143: MES | G143: HH:. | H143: COSTO
B145: MENSUAL | F145: 1 | G145: 18 | H145: 120 | I145: =F145*G145*H145 -> 2160
B146: DERECHOS
B147: INICIACIONES | G147: 0 | H147: 250 | I147: =#REF!*H147 -> #REF!
B148: AUMENTO DE SALARIO | G148: 0 | H148: 250 | I148: =G148*H148 -> 0
B149: EXALTACIONES | G149: 0 | H149: 250 | I149: =G149*H149 -> 0
B150: REGULARIZACIONES | G150: 0 | H150: 250 | I150: =G150*H150 -> 0
B151: AFILIACION | G151: 0 | H151: 250 | I151: =G151*H151 -> 0
B153: DIVERSOS
B155: REVISTA UNIDAD MEXICANA (SIMBOLISMO) | F155: =F145 -> 1 | G155: =G145 -> 18 | H155: 18 | I155: =F155*G155*H155 -> 324
B156: CONF:. GGR:. LLOG:. REP.MEX. | F156: 1 | G156: --- | H156: 150 | I156: =F156*H156 -> 150
B157: CONF:. MAS:. INTERAMERICANA | F157: 1 | G157: --- | H157: 70 | I157: =F157*H157 -> 70
B158: SERVICIOS | F158: =F145 -> 1 | G158: --- | H158: 800 | I158: =F158*H158 -> 800
B160: OTROS: FONDO DE CONTINGENCIA | F160: 0 | G160: --- | H160: 500 | I160: =F160*H160 -> 0
B162: AUX:. MAS:. "POST MORTEM"
B164: CUOTAS INICIALES | G164: 0 | H164: 150 | J164: =G164*H164 -> 0
...

Sheet DEFUNCIONES
D1: Dig.·. Resp.·. Abn.·. y Sesquicent.·. Log.·. Simb.·. FRATERNIDAD No. 1
D2: D E F U N C I O N E S
D3: 2 0 2 6
A4: No. | B4: GRAN CIRC. | C4: FECHA | D4: DEFUNC | E4: NOMBRE | F4: LOGIA | G4: ORIENTE | H4: PAGADO
A5: 1 | B5: 17/2025 | C5: 46036 | D5: 2753 | E5: JESUS MARTIN CARRION BRAVO | F5: YANGA No. 15 | G5: CORDOBA, VER | H5: 45899
A6: 2 | B6: 18/2025 | C6: 46036 | D6: 2754 | E6: MARCELINO CEBALLOS ZAMARRON | F6: FRATERNIDAD No. 11 | G6: JALAPA, VER. | H6: 45930
A7: 3 | B7: 19/2026 | C7: 46045 | D7: 2755 | E7: VICTOR MANUEL ESPINOZA BASTIAN | F7: MAHATMA GANDHI No. 3 | G7: POZA RICA, Ver. | H7: 45960
A8: 4 | B8: 20/2026 | C8: 46046 | D8: 2756 | E8: EFREN USCANGA BRAVO | F8: CATEMACO No. 68 | G8: CATEMACO, VER. | H8: 45986
A9: 5 | B9: 29/2026 | C9: 46092 | D9: 2757 | E9: JUAN CARLOS ENCISO MENDEZ | F9: DEP. DEL OTE. 17 | G9: JALAPA, VER. | H9: 46053
A10: 6 | B10: 40/2026 | C10: 265330 | D10: 2758 | E10: MARIO RODRIGUEZ CASTELLANOS | F10: FRATER Y PROG 50 | G10: TUXPAN, VER. | H10: 46080
D11: 2759 | H11: 46111
D12: 2760 | H12: 46140
D13: 2761 | H13: 46201
